LICENSE
LICENSE.txt
MANIFEST.in
README.txt
setup.cfg
setup.py
ProcessAudio/AllDataAugmentation.py
ProcessAudio/AudioAugmentation.py
ProcessAudio/Audio_pipeline.py
ProcessAudio/Features.py
ProcessAudio/Graph.py
ProcessAudio/README.md
ProcessAudio/Split.py
ProcessAudio/Util.py
ProcessAudio/__init__.py
ProcessAudio.egg-info/PKG-INFO
ProcessAudio.egg-info/SOURCES.txt
ProcessAudio.egg-info/dependency_links.txt
ProcessAudio.egg-info/requires.txt
ProcessAudio.egg-info/top_level.txt