Metadata-Version: 2.1
Name: ProcessAudio
Version: 0.24.5
Summary: Audio processing
Home-page: https://github.com/wisrovi/ProcessAudio
Download-URL: https://github.com/wisrovi/ProcessAudio/releases/tag/V0.24.03
Author: William Rodriguez
Author-email: wisrovi.rodriguez@gmail.com
License: GPLv3
Keywords: encoding,i18n,xml
Classifier: Programming Language :: Python
Classifier: Programming Language :: Python :: 3
Classifier: License :: OSI Approved :: GNU General Public License v3 (GPLv3)
Classifier: Operating System :: OS Independent
Classifier: Development Status :: 4 - Beta
Classifier: Intended Audience :: Developers
Classifier: Topic :: Software Development :: Libraries :: Python Modules
License-File: LICENSE
License-File: LICENSE.txt
Requires-Dist: librosa
Requires-Dist: matplotlib
Requires-Dist: nlpaug
Requires-Dist: scipy
Requires-Dist: pydub
Requires-Dist: noisereduce
Requires-Dist: torch
Requires-Dist: opencv-python
Requires-Dist: setuptools
